JK_ff/jk_ff.v
module jk_ff(
    input j,
    input k,
    input clk,
    output reg q,
    output q_b
);

initial
    q = 1'b0;

assign q_b = ~q;

always @(posedge clk)
begin
    if (j == 1'b0 && k == 1'b0)
        q <= q;          // Hold
    else if (j == 1'b0 && k == 1'b1)
        q <= 1'b0;       // Reset
    else if (j == 1'b1 && k == 1'b0)
        q <= 1'b1;       // Set
    else
        q <= ~q;         // Toggle
end

endmodule

JK_ff/jk_ff_tb.v
`timescale 1ns/1ps

module jk_ff_tb;

reg j;
reg k;
reg clk;

wire q;
wire q_b;

// DUT Instantiation
jk_ff uut (
    .j(j),
    .k(k),
    .clk(clk),
    .q(q),
    .q_b(q_b)
);

// Clock Generation
initial begin
    clk = 0;
    forever #10 clk = ~clk;
end

// Stimulus
initial begin

    // Hold
    j = 0;
    k = 0;
    #20;

    // Reset
    j = 0;
    k = 1;
    #20;

    // Set
    j = 1;
    k = 0;
    #20;

    // Toggle
    j = 1;
    k = 1;
    #60;

    $finish;

end

// Waveform Generation
initial begin

    $dumpfile("jk_ff.vcd");
    $dumpvars(0, jk_ff_tb);

    $monitor("Time=%0t clk=%b j=%b k=%b q=%b q_b=%b",
             $time, clk, j, k, q, q_b);

end

endmodule

JK_ff/jk_ff.vcd
$date
	Sun Jul 05 21:43:55 2026
$end
$version
	Icarus Verilog
$end
$timescale
	1ps
$end
$scope module jk_ff_tb $end
$var wire 1 ! q_b $end
$var wire 1 " q $end
$var reg 1 # clk $end
$var reg 1 $ j $end
$var reg 1 % k $end
$scope module uut $end
$var wire 1 # clk $end
$var wire 1 $ j $end
$var wire 1 % k $end
$var wire 1 ! q_b $end
$var reg 1 " q $end
$upscope $end
$upscope $end
$enddefinitions $end
$comment Show the parameter values. $end
$dumpall
$end
#0
$dumpvars
0%
0$
0#
0"
1!
$end
#10000
1#
#20000
0#
1%
#30000
1#
#40000
0#
0%
1$
#50000
0!
1"
1#
#60000
0#
1%
#70000
1!
0"
1#
#80000
0#
#90000
0!
1"
1#
#100000
0#
#110000
1!
0"
1#
